{
"meta":{"test_sets":[],"test_metrics":[],"learn_metrics":[{"best_value":"Min","name":"MultiClass"}],"launch_mode":"Train","parameters":"","iteration_count":300,"learn_sets":["learn"],"name":"experiment"},
"iterations":[
{"learn":[1.881991778],"iteration":0,"passed_time":0.06767521743,"remaining_time":20.23489001},
{"learn":[1.827241278],"iteration":1,"passed_time":0.07286139055,"remaining_time":10.85634719},
{"learn":[1.778385169],"iteration":2,"passed_time":0.07797110278,"remaining_time":7.719139176},
{"learn":[1.736059037],"iteration":3,"passed_time":0.08258609017,"remaining_time":6.111370673},
{"learn":[1.699675703],"iteration":4,"passed_time":0.08741837648,"remaining_time":5.157684212},
{"learn":[1.665007168],"iteration":5,"passed_time":0.09200132113,"remaining_time":4.508064736},
{"learn":[1.632773976],"iteration":6,"passed_time":0.09682273208,"remaining_time":4.052722928},
{"learn":[1.605229042],"iteration":7,"passed_time":0.1015105552,"remaining_time":3.705135266},
{"learn":[1.578336642],"iteration":8,"passed_time":0.106316049,"remaining_time":3.43755225},
{"learn":[1.553027305],"iteration":9,"passed_time":0.111200087,"remaining_time":3.224802523},
{"learn":[1.53295131],"iteration":10,"passed_time":0.115962121,"remaining_time":3.046641178},
{"learn":[1.509502014],"iteration":11,"passed_time":0.1208274084,"remaining_time":2.899857801},
{"learn":[1.487017659],"iteration":12,"passed_time":0.1258014494,"remaining_time":2.777308922},
{"learn":[1.466926739],"iteration":13,"passed_time":0.1305586916,"remaining_time":2.667127556},
{"learn":[1.447259217],"iteration":14,"passed_time":0.135004465,"remaining_time":2.565084834},
{"learn":[1.429650598],"iteration":15,"passed_time":0.1397363313,"remaining_time":2.48031988},
{"learn":[1.412200396],"iteration":16,"passed_time":0.1444694476,"remaining_time":2.404991392},
{"learn":[1.395298116],"iteration":17,"passed_time":0.1487894668,"remaining_time":2.33103498},
{"learn":[1.379340768],"iteration":18,"passed_time":0.1533297434,"remaining_time":2.267666204},
{"learn":[1.364938637],"iteration":19,"passed_time":0.1581382789,"remaining_time":2.213935904},
{"learn":[1.348260548],"iteration":20,"passed_time":0.1631772388,"remaining_time":2.167926172},
{"learn":[1.335537682],"iteration":21,"passed_time":0.1684316642,"remaining_time":2.128363756},
{"learn":[1.321308545],"iteration":22,"passed_time":0.1732577419,"remaining_time":2.086625848},
{"learn":[1.309284554],"iteration":23,"passed_time":0.1777938933,"remaining_time":2.044629773},
{"learn":[1.295461666],"iteration":24,"passed_time":0.1831206962,"remaining_time":2.014327658},
{"learn":[1.285918715],"iteration":25,"passed_time":0.1882160329,"remaining_time":1.983507424},
{"learn":[1.275206887],"iteration":26,"passed_time":0.1929552328,"remaining_time":1.950991798},
{"learn":[1.264749052],"iteration":27,"passed_time":0.1975198435,"remaining_time":1.918764194},
{"learn":[1.254536449],"iteration":28,"passed_time":0.2024001731,"remaining_time":1.891394721},
{"learn":[1.246401064],"iteration":29,"passed_time":0.2064777675,"remaining_time":1.858299908},
{"learn":[1.236838039],"iteration":30,"passed_time":0.2110855047,"remaining_time":1.831677444},
{"learn":[1.227661788],"iteration":31,"passed_time":0.2157450352,"remaining_time":1.80686467},
{"learn":[1.220468858],"iteration":32,"passed_time":0.2204273582,"remaining_time":1.783457716},
{"learn":[1.212005687],"iteration":33,"passed_time":0.2252987291,"remaining_time":1.762631234},
{"learn":[1.201663128],"iteration":34,"passed_time":0.2302206851,"remaining_time":1.743099473},
{"learn":[1.192010737],"iteration":35,"passed_time":0.2350128451,"remaining_time":1.72342753},
{"learn":[1.186148509],"iteration":36,"passed_time":0.2395001615,"remaining_time":1.70239304},
{"learn":[1.179449408],"iteration":37,"passed_time":0.2440679807,"remaining_time":1.682784498},
{"learn":[1.170708746],"iteration":38,"passed_time":0.2487543454,"remaining_time":1.664740619},
{"learn":[1.162855052],"iteration":39,"passed_time":0.2536765931,"remaining_time":1.648897855},
{"learn":[1.155733012],"iteration":40,"passed_time":0.2583136229,"remaining_time":1.631786057},
{"learn":[1.147686905],"iteration":41,"passed_time":0.2631109497,"remaining_time":1.616252977},
{"learn":[1.141430282],"iteration":42,"passed_time":0.2675223053,"remaining_time":1.598912383},
{"learn":[1.135013005],"iteration":43,"passed_time":0.2722942979,"remaining_time":1.584257733},
{"learn":[1.12959271],"iteration":44,"passed_time":0.277019539,"remaining_time":1.569777387},
{"learn":[1.122586751],"iteration":45,"passed_time":0.2815841497,"remaining_time":1.554834218},
{"learn":[1.114236406],"iteration":46,"passed_time":0.2866037756,"remaining_time":1.542782026},
{"learn":[1.109428872],"iteration":47,"passed_time":0.2913093076,"remaining_time":1.529373865},
{"learn":[1.105884138],"iteration":48,"passed_time":0.2958631263,"remaining_time":1.51554377},
{"learn":[1.101053496],"iteration":49,"passed_time":0.3003715685,"remaining_time":1.501857842},
{"learn":[1.095806992],"iteration":50,"passed_time":0.3050881009,"remaining_time":1.489547787},
{"learn":[1.09096558],"iteration":51,"passed_time":0.3095216656,"remaining_time":1.476180251},
{"learn":[1.084725768],"iteration":52,"passed_time":0.3140282744,"remaining_time":1.46349026},
{"learn":[1.079962867],"iteration":53,"passed_time":0.3186986803,"remaining_time":1.451849543},
{"learn":[1.075376117],"iteration":54,"passed_time":0.3230871601,"remaining_time":1.43920644},
{"learn":[1.070909177],"iteration":55,"passed_time":0.3274020958,"remaining_time":1.426537703},
{"learn":[1.067345885],"iteration":56,"passed_time":0.331730907,"remaining_time":1.414221235},
{"learn":[1.062596124],"iteration":57,"passed_time":0.3361059697,"remaining_time":1.402373184},
{"learn":[1.058289304],"iteration":58,"passed_time":0.3406870809,"remaining_time":1.39162011},
{"learn":[1.053007182],"iteration":59,"passed_time":0.3455241591,"remaining_time":1.382096636},
{"learn":[1.049205099],"iteration":60,"passed_time":0.3501110622,"remaining_time":1.371746621},
{"learn":[1.04459448],"iteration":61,"passed_time":0.3544849999,"remaining_time":1.360765},
{"learn":[1.04020651],"iteration":62,"passed_time":0.359071528,"remaining_time":1.350792891},
{"learn":[1.036750102],"iteration":63,"passed_time":0.3635551776,"remaining_time":1.340609718},
{"learn":[1.033091966],"iteration":64,"passed_time":0.3679136565,"remaining_time":1.330149373},
{"learn":[1.029945526],"iteration":65,"passed_time":0.3724147234,"remaining_time":1.320379474},
{"learn":[1.027181695],"iteration":66,"passed_time":0.3772923029,"remaining_time":1.312076217},
{"learn":[1.022759177],"iteration":67,"passed_time":0.3819285826,"remaining_time":1.303050458},
{"learn":[1.018089782],"iteration":68,"passed_time":0.3863290212,"remaining_time":1.293362375},
{"learn":[1.013163917],"iteration":69,"passed_time":0.3909295914,"remaining_time":1.284482943},
{"learn":[1.009066395],"iteration":70,"passed_time":0.3954175329,"remaining_time":1.275360775},
{"learn":[1.005650666],"iteration":71,"passed_time":0.4003270301,"remaining_time":1.267702262},
{"learn":[1.001943542],"iteration":72,"passed_time":0.4048420142,"remaining_time":1.258892291},
{"learn":[0.9976976368],"iteration":73,"passed_time":0.409887891,"remaining_time":1.251819775},
{"learn":[0.9949608514],"iteration":74,"passed_time":0.414642383,"remaining_time":1.243927149},
{"learn":[0.9913911523],"iteration":75,"passed_time":0.4195526719,"remaining_time":1.236576296},
{"learn":[0.9871518602],"iteration":76,"passed_time":0.4242528288,"remaining_time":1.22868027},
{"learn":[0.9837095274],"iteration":77,"passed_time":0.4290231547,"remaining_time":1.221065902},
{"learn":[0.9801929135],"iteration":78,"passed_time":0.433624725,"remaining_time":1.213051446},
{"learn":[0.9779000553],"iteration":79,"passed_time":0.4379307437,"remaining_time":1.204309545},
{"learn":[0.9755961625],"iteration":80,"passed_time":0.4424346858,"remaining_time":1.196212299},
{"learn":[0.9726571514],"iteration":81,"passed_time":0.447174469,"remaining_time":1.188829686},
{"learn":[0.969507211],"iteration":82,"passed_time":0.4518135405,"remaining_time":1.181247449},
{"learn":[0.9662887348],"iteration":83,"passed_time":0.4564999469,"remaining_time":1.173857006},
{"learn":[0.9636757851],"iteration":84,"passed_time":0.4610323482,"remaining_time":1.166140646},
{"learn":[0.9620687185],"iteration":85,"passed_time":0.46542762,"remaining_time":1.158157101},
{"learn":[0.9597458488],"iteration":86,"passed_time":0.4698949774,"remaining_time":1.150432531},
{"learn":[0.9573740592],"iteration":87,"passed_time":0.4745010478,"remaining_time":1.143116161},
{"learn":[0.9535084244],"iteration":88,"passed_time":0.479028324,"remaining_time":1.135673892},
{"learn":[0.9507617949],"iteration":89,"passed_time":0.4837039801,"remaining_time":1.12864262},
{"learn":[0.9478928205],"iteration":90,"passed_time":0.4882843413,"remaining_time":1.121444256},
{"learn":[0.9449968058],"iteration":91,"passed_time":0.493039,"remaining_time":1.11469687},
{"learn":[0.9424638756],"iteration":92,"passed_time":0.4973012673,"remaining_time":1.106896369},
{"learn":[0.9392216003],"iteration":93,"passed_time":0.5015374504,"remaining_time":1.099113987},
{"learn":[0.9364728894],"iteration":94,"passed_time":0.5064159049,"remaining_time":1.092792216},
{"learn":[0.9340193684],"iteration":95,"passed_time":0.5206864646,"remaining_time":1.106458737},
{"learn":[0.9317591023],"iteration":96,"passed_time":0.525192115,"remaining_time":1.099113395},
{"learn":[0.9299443941],"iteration":97,"passed_time":0.5291381634,"remaining_time":1.090672541},
{"learn":[0.9270572473],"iteration":98,"passed_time":0.5337255665,"remaining_time":1.083624635},
{"learn":[0.9246882016],"iteration":99,"passed_time":0.5384680582,"remaining_time":1.076936116},
{"learn":[0.9221710873],"iteration":100,"passed_time":0.5434606831,"remaining_time":1.07077897},
{"learn":[0.9204298902],"iteration":101,"passed_time":0.548389681,"remaining_time":1.064521146},
{"learn":[0.9176721752],"iteration":102,"passed_time":0.5531971332,"remaining_time":1.058056653},
{"learn":[0.9156366439],"iteration":103,"passed_time":0.5579404582,"remaining_time":1.051503171},
{"learn":[0.9110727829],"iteration":104,"passed_time":0.5628346215,"remaining_time":1.045264297},
{"learn":[0.9082827738],"iteration":105,"passed_time":0.5673306466,"remaining_time":1.038322127},
{"learn":[0.9051319967],"iteration":106,"passed_time":0.5718802985,"remaining_time":1.031522408},
{"learn":[0.9024383813],"iteration":107,"passed_time":0.5767896707,"remaining_time":1.025403859},
{"learn":[0.8993676909],"iteration":108,"passed_time":0.5816263322,"remaining_time":1.019180087},
{"learn":[0.8970101562],"iteration":109,"passed_time":0.5861924846,"remaining_time":1.012514292},
{"learn":[0.8942402525],"iteration":110,"passed_time":0.5908816411,"remaining_time":1.006095767},
{"learn":[0.8924262414],"iteration":111,"passed_time":0.5953846664,"remaining_time":0.9993956901},
{"learn":[0.8905302342],"iteration":112,"passed_time":0.5998109392,"remaining_time":0.9926074835},
{"learn":[0.8876310883],"iteration":113,"passed_time":0.604417843,"remaining_time":0.986155428},
{"learn":[0.885209683],"iteration":114,"passed_time":0.6092332954,"remaining_time":0.9800709535},
{"learn":[0.883630696],"iteration":115,"passed_time":0.6141442927,"remaining_time":0.9741599125},
{"learn":[0.8818506696],"iteration":116,"passed_time":0.618588816,"remaining_time":0.9675363533},
{"learn":[0.8800730943],"iteration":117,"passed_time":0.6233240574,"remaining_time":0.9613981225},
{"learn":[0.8785013471],"iteration":118,"passed_time":0.6279419199,"remaining_time":0.955104937},
{"learn":[0.8769691535],"iteration":119,"passed_time":0.6323413168,"remaining_time":0.9485119752},
{"learn":[0.8749734443],"iteration":120,"passed_time":0.6369913887,"remaining_time":0.9423261039},
{"learn":[0.8726971513],"iteration":121,"passed_time":0.6418498842,"remaining_time":0.9364695032},
{"learn":[0.8703323534],"iteration":122,"passed_time":0.6467229635,"remaining_time":0.9306501182},
{"learn":[0.8685836355],"iteration":123,"passed_time":0.6512685319,"remaining_time":0.9243811421},
{"learn":[0.8658885613],"iteration":124,"passed_time":0.6561772791,"remaining_time":0.9186481908},
{"learn":[0.8643115172],"iteration":125,"passed_time":0.6607041802,"remaining_time":0.9124010108},
{"learn":[0.8621159308],"iteration":126,"passed_time":0.6657716411,"remaining_time":0.9069172748},
{"learn":[0.8608825606],"iteration":127,"passed_time":0.6707577242,"remaining_time":0.9013306918},
{"learn":[0.8594266622],"iteration":128,"passed_time":0.6757799752,"remaining_time":0.8958013624},
{"learn":[0.8575458621],"iteration":129,"passed_time":0.6807179317,"remaining_time":0.8901696029},
{"learn":[0.8551836303],"iteration":130,"passed_time":0.684950823,"remaining_time":0.8836388479},
{"learn":[0.8531482028],"iteration":131,"passed_time":0.6900853694,"remaining_time":0.8782904701},
{"learn":[0.8500749983],"iteration":132,"passed_time":0.6949626988,"remaining_time":0.8726223361},
{"learn":[0.848896338],"iteration":133,"passed_time":0.6995163925,"remaining_time":0.8665650833},
{"learn":[0.8472108274],"iteration":134,"passed_time":0.7039667911,"remaining_time":0.8604038557},
{"learn":[0.8453818285],"iteration":135,"passed_time":0.7089698747,"remaining_time":0.8549342607},
{"learn":[0.8438503242],"iteration":136,"passed_time":0.7136592396,"remaining_time":0.8490982194},
{"learn":[0.8423187973],"iteration":137,"passed_time":0.7184262321,"remaining_time":0.8433699246},
{"learn":[0.8403032436],"iteration":138,"passed_time":0.7227931695,"remaining_time":0.8371920884},
{"learn":[0.8370975496],"iteration":139,"passed_time":0.7279338411,"remaining_time":0.8319243899},
{"learn":[0.83589516],"iteration":140,"passed_time":0.732474701,"remaining_time":0.8259821097},
{"learn":[0.8341841808],"iteration":141,"passed_time":0.7379018822,"remaining_time":0.8210457563},
{"learn":[0.8318471085],"iteration":142,"passed_time":0.7430867636,"remaining_time":0.8158365167},
{"learn":[0.8303600094],"iteration":143,"passed_time":0.7477733784,"remaining_time":0.8100878266},
{"learn":[0.8278746928],"iteration":144,"passed_time":0.7532557281,"remaining_time":0.805204399},
{"learn":[0.8260619967],"iteration":145,"passed_time":0.7583461897,"remaining_time":0.7998994055},
{"learn":[0.8246415802],"iteration":146,"passed_time":0.763380066,"remaining_time":0.7945384361},
{"learn":[0.8231383268],"iteration":147,"passed_time":0.7683950668,"remaining_time":0.789162501},
{"learn":[0.8203340041],"iteration":148,"passed_time":0.7731569757,"remaining_time":0.7835349217},
{"learn":[0.8190741841],"iteration":149,"passed_time":0.7781656429,"remaining_time":0.7781656429},
{"learn":[0.8178737923],"iteration":150,"passed_time":0.7824224517,"remaining_time":0.7720592404},
{"learn":[0.8163659314],"iteration":151,"passed_time":0.787024022,"remaining_time":0.7663128635},
{"learn":[0.8145516108],"iteration":152,"passed_time":0.7919562699,"remaining_time":0.7608991613},
{"learn":[0.8127356128],"iteration":153,"passed_time":0.7968041401,"remaining_time":0.7554117172},
{"learn":[0.811689443],"iteration":154,"passed_time":0.8018706426,"remaining_time":0.7501370527},
{"learn":[0.8098915588],"iteration":155,"passed_time":0.806685845,"remaining_time":0.7446330877},
{"learn":[0.8089003048],"iteration":156,"passed_time":0.8120616078,"remaining_time":0.7396484708},
{"learn":[0.8077265292],"iteration":157,"passed_time":0.8167370138,"remaining_time":0.7340294681},
{"learn":[0.8062942648],"iteration":158,"passed_time":0.8213104582,"remaining_time":0.7283319157},
{"learn":[0.8043431721],"iteration":159,"passed_time":0.8267392644,"remaining_time":0.7233968563},
{"learn":[0.8020564602],"iteration":160,"passed_time":0.831809892,"remaining_time":0.7181464285},
{"learn":[0.8004446461],"iteration":161,"passed_time":0.8373750778,"remaining_time":0.7133195107},
{"learn":[0.7994867595],"iteration":162,"passed_time":0.8436371618,"remaining_time":0.709069271},
{"learn":[0.7980691332],"iteration":163,"passed_time":0.8486311202,"remaining_time":0.7037428801},
{"learn":[0.7967711197],"iteration":164,"passed_time":0.8531207284,"remaining_time":0.6980078687},
{"learn":[0.7955600203],"iteration":165,"passed_time":0.8579783905,"remaining_time":0.6925849658},
{"learn":[0.7935517519],"iteration":166,"passed_time":0.8631698138,"remaining_time":0.6874346421},
{"learn":[0.7921300911],"iteration":167,"passed_time":0.8682762343,"remaining_time":0.6822170412},
{"learn":[0.7894293889],"iteration":168,"passed_time":0.8734337398,"remaining_time":0.6770403545},
{"learn":[0.7879579622],"iteration":169,"passed_time":0.8781105209,"remaining_time":0.6714962807},
{"learn":[0.7864672695],"iteration":170,"passed_time":0.8830322269,"remaining_time":0.6661471185},
{"learn":[0.7848324425],"iteration":171,"passed_time":0.8881201467,"remaining_time":0.6609266208},
{"learn":[0.783229287],"iteration":172,"passed_time":0.8935576199,"remaining_time":0.6559642643},
{"learn":[0.781353084],"iteration":173,"passed_time":0.8982002332,"remaining_time":0.6504208585},
{"learn":[0.7796683552],"iteration":174,"passed_time":0.9032649439,"remaining_time":0.6451892457},
{"learn":[0.7784549414],"iteration":175,"passed_time":0.9077883032,"remaining_time":0.6395781227},
{"learn":[0.7772886441],"iteration":176,"passed_time":0.9125463787,"remaining_time":0.6341423988},
{"learn":[0.7764574153],"iteration":177,"passed_time":0.9175597961,"remaining_time":0.6288892985},
{"learn":[0.7751858742],"iteration":178,"passed_time":0.9224883356,"remaining_time":0.6235815006},
{"learn":[0.7735984698],"iteration":179,"passed_time":0.9270281122,"remaining_time":0.6180187414},
{"learn":[0.7724247147],"iteration":180,"passed_time":0.9321804508,"remaining_time":0.6128700202},
{"learn":[0.7706403986],"iteration":181,"passed_time":0.9370516134,"remaining_time":0.6075389582},
{"learn":[0.7692770495],"iteration":182,"passed_time":0.9418661075,"remaining_time":0.6021766917},
{"learn":[0.7682361013],"iteration":183,"passed_time":0.9468215229,"remaining_time":0.596909221},
{"learn":[0.7669129709],"iteration":184,"passed_time":0.9523204148,"remaining_time":0.5919829605},
{"learn":[0.7653023021],"iteration":185,"passed_time":0.9576658432,"remaining_time":0.5869564846},
{"learn":[0.7642362871],"iteration":186,"passed_time":0.9625332557,"remaining_time":0.5816377428},
{"learn":[0.7623087206],"iteration":187,"passed_time":0.9674880878,"remaining_time":0.5763758821},
{"learn":[0.7609520389],"iteration":188,"passed_time":0.9724382114,"remaining_time":0.5711145051},
{"learn":[0.7590926559],"iteration":189,"passed_time":0.9773046655,"remaining_time":0.5658079642},
{"learn":[0.7571210115],"iteration":190,"passed_time":0.9825966755,"remaining_time":0.5607488881},
{"learn":[0.7564561724],"iteration":191,"passed_time":0.9872592061,"remaining_time":0.5553333034},
{"learn":[0.7550043936],"iteration":192,"passed_time":0.9925540078,"remaining_time":0.5502760562},
{"learn":[0.7535731326],"iteration":193,"passed_time":0.9974272539,"remaining_time":0.5449860253},
{"learn":[0.7523993686],"iteration":194,"passed_time":1.001999406,"remaining_time":0.539538142},
{"learn":[0.7514875008],"iteration":195,"passed_time":1.006752148,"remaining_time":0.5341950176},
{"learn":[0.7504612755],"iteration":196,"passed_time":1.011568559,"remaining_time":0.5288911756},
{"learn":[0.7489231076],"iteration":197,"passed_time":1.016677646,"remaining_time":0.52374303},
{"learn":[0.7473456733],"iteration":198,"passed_time":1.02164102,"remaining_time":0.518521322},
{"learn":[0.7466089829],"iteration":199,"passed_time":1.025823535,"remaining_time":0.5129117675},
{"learn":[0.7456486645],"iteration":200,"passed_time":1.030434272,"remaining_time":0.5075273282},
{"learn":[0.7435273124],"iteration":201,"passed_time":1.035306018,"remaining_time":0.5022771772},
{"learn":[0.7425510583],"iteration":202,"passed_time":1.039987758,"remaining_time":0.4969399631},
{"learn":[0.7409691227],"iteration":203,"passed_time":1.044350154,"remaining_time":0.4914588958},
{"learn":[0.7397028318],"iteration":204,"passed_time":1.049052852,"remaining_time":0.4861464437},
{"learn":[0.7384241754],"iteration":205,"passed_time":1.053770051,"remaining_time":0.4808465283},
{"learn":[0.7366989011],"iteration":206,"passed_time":1.05842129,"remaining_time":0.4755226085},
{"learn":[0.7351556448],"iteration":207,"passed_time":1.063086071,"remaining_time":0.4702111466},
{"learn":[0.7343756859],"iteration":208,"passed_time":1.067282377,"remaining_time":0.4647018964},
{"learn":[0.7333699198],"iteration":209,"passed_time":1.072058203,"remaining_time":0.4594535158},
{"learn":[0.7322939498],"iteration":210,"passed_time":1.076485976,"remaining_time":0.4540628052},
{"learn":[0.7311722176],"iteration":211,"passed_time":1.081492852,"remaining_time":0.4489215611},
{"learn":[0.7304280221],"iteration":212,"passed_time":1.086234635,"remaining_time":0.4436733016},
{"learn":[0.728927676],"iteration":213,"passed_time":1.090879373,"remaining_time":0.4383907762},
{"learn":[0.728244282],"iteration":214,"passed_time":1.095306063,"remaining_time":0.4330279783},
{"learn":[0.726895397],"iteration":215,"passed_time":1.100661408,"remaining_time":0.4280349921},
{"learn":[0.7261629854],"iteration":216,"passed_time":1.105586073,"remaining_time":0.4228739356},
{"learn":[0.7253471],"iteration":217,"passed_time":1.110732994,"remaining_time":0.4177986493},
{"learn":[0.7246817347],"iteration":218,"passed_time":1.116111174,"remaining_time":0.4128082424},
{"learn":[0.7239015296],"iteration":219,"passed_time":1.121166718,"remaining_time":0.4076969883},
{"learn":[0.7222358998],"iteration":220,"passed_time":1.126459019,"remaining_time":0.4026708712},
{"learn":[0.7214920254],"iteration":221,"passed_time":1.131589316,"remaining_time":0.3975854352},
{"learn":[0.7207851898],"iteration":222,"passed_time":1.137088083,"remaining_time":0.3926268267},
{"learn":[0.7198455345],"iteration":223,"passed_time":1.142919402,"remaining_time":0.3877762258},
{"learn":[0.7188354368],"iteration":224,"passed_time":1.147510972,"remaining_time":0.3825036574},
{"learn":[0.7179219364],"iteration":225,"passed_time":1.153142619,"remaining_time":0.3775776716},
{"learn":[0.7166170156],"iteration":226,"passed_time":1.158062449,"remaining_time":0.3724165586},
{"learn":[0.7159416405],"iteration":227,"passed_time":1.162705854,"remaining_time":0.3671702698},
{"learn":[0.7144029704],"iteration":228,"passed_time":1.167857235,"remaining_time":0.3620867409},
{"learn":[0.7133411738],"iteration":229,"passed_time":1.172503723,"remaining_time":0.3568489592},
{"learn":[0.7115805676],"iteration":230,"passed_time":1.177519766,"remaining_time":0.3517266832},
{"learn":[0.7108579158],"iteration":231,"passed_time":1.182048708,"remaining_time":0.3464625525},
{"learn":[0.709848252],"iteration":232,"passed_time":1.186328185,"remaining_time":0.3411329973},
{"learn":[0.7089829541],"iteration":233,"passed_time":1.190945922,"remaining_time":0.3359078242},
{"learn":[0.7084528013],"iteration":234,"passed_time":1.195403446,"remaining_time":0.3306435063},
{"learn":[0.7074459737],"iteration":235,"passed_time":1.200220065,"remaining_time":0.3254834075},
{"learn":[0.7065528056],"iteration":236,"passed_time":1.204863178,"remaining_time":0.3202800854},
{"learn":[0.70542805],"iteration":237,"passed_time":1.209737841,"remaining_time":0.3151417905},
{"learn":[0.7039522881],"iteration":238,"passed_time":1.214568502,"remaining_time":0.3099944713},
{"learn":[0.7027158865],"iteration":239,"passed_time":1.21945079,"remaining_time":0.3048626976},
{"learn":[0.7013482738],"iteration":240,"passed_time":1.223802769,"remaining_time":0.2996031675},
{"learn":[0.7005846802],"iteration":241,"passed_time":1.228136122,"remaining_time":0.2943466738},
{"learn":[0.6993300198],"iteration":242,"passed_time":1.233400256,"remaining_time":0.2893161094},
{"learn":[0.6975056064],"iteration":243,"passed_time":1.238638597,"remaining_time":0.2842777109},
{"learn":[0.6968138894],"iteration":244,"passed_time":1.24336213,"remaining_time":0.2791221109},
{"learn":[0.6956478987],"iteration":245,"passed_time":1.248174749,"remaining_time":0.2739895791},
{"learn":[0.6945178025],"iteration":246,"passed_time":1.25280082,"remaining_time":0.2688196092},
{"learn":[0.693977388],"iteration":247,"passed_time":1.257664941,"remaining_time":0.2637039392},
{"learn":[0.6930282311],"iteration":248,"passed_time":1.262452559,"remaining_time":0.2585746205},
{"learn":[0.6919658152],"iteration":249,"passed_time":1.267153049,"remaining_time":0.2534306099},
{"learn":[0.6904826483],"iteration":250,"passed_time":1.271680284,"remaining_time":0.2482563104},
{"learn":[0.6891683467],"iteration":251,"passed_time":1.276458068,"remaining_time":0.2431348702},
{"learn":[0.6882622415],"iteration":252,"passed_time":1.280934551,"remaining_time":0.2379601735},
{"learn":[0.6874130167],"iteration":253,"passed_time":1.285636958,"remaining_time":0.23283189},
{"learn":[0.6865717302],"iteration":254,"passed_time":1.290354824,"remaining_time":0.2277096748},
{"learn":[0.6857602004],"iteration":255,"passed_time":1.295154651,"remaining_time":0.2226047056},
{"learn":[0.6851121847],"iteration":256,"passed_time":1.299790972,"remaining_time":0.2174747541},
{"learn":[0.6844613462],"iteration":257,"passed_time":1.304491546,"remaining_time":0.2123590888},
{"learn":[0.6837257559],"iteration":258,"passed_time":1.308796939,"remaining_time":0.2071840715},
{"learn":[0.6829947667],"iteration":259,"passed_time":1.313395301,"remaining_time":0.2020608156},
{"learn":[0.6820171795],"iteration":260,"passed_time":1.318066999,"remaining_time":0.1969525401},
{"learn":[0.681674869],"iteration":261,"passed_time":1.322319266,"remaining_time":0.1917867638},
{"learn":[0.6805004702],"iteration":262,"passed_time":1.327101676,"remaining_time":0.1867025171},
{"learn":[0.6793726821],"iteration":263,"passed_time":1.332259139,"remaining_time":0.1816717008},
{"learn":[0.6786489625],"iteration":264,"passed_time":1.336727205,"remaining_time":0.1765488762},
{"learn":[0.6775346656],"iteration":265,"passed_time":1.341262107,"remaining_time":0.1714395174},
{"learn":[0.6766378984],"iteration":266,"passed_time":1.345688254,"remaining_time":0.1663210202},
{"learn":[0.6754993786],"iteration":267,"passed_time":1.350238948,"remaining_time":0.1612225609},
{"learn":[0.6748390658],"iteration":268,"passed_time":1.354628636,"remaining_time":0.1561096198},
{"learn":[0.6737850855],"iteration":269,"passed_time":1.359375003,"remaining_time":0.151041667},
{"learn":[0.672578246],"iteration":270,"passed_time":1.364260833,"remaining_time":0.1459910116},
{"learn":[0.6715280773],"iteration":271,"passed_time":1.368928572,"remaining_time":0.1409191177},
{"learn":[0.6704691262],"iteration":272,"passed_time":1.373319093,"remaining_time":0.1358227675},
{"learn":[0.6697993392],"iteration":273,"passed_time":1.377649071,"remaining_time":0.1307258243},
{"learn":[0.6686109684],"iteration":274,"passed_time":1.382167139,"remaining_time":0.1256515581},
{"learn":[0.6681085207],"iteration":275,"passed_time":1.386740541,"remaining_time":0.120586134},
{"learn":[0.6672461668],"iteration":276,"passed_time":1.391330986,"remaining_time":0.1155256776},
{"learn":[0.6664219025],"iteration":277,"passed_time":1.396163523,"remaining_time":0.1104877608},
{"learn":[0.6654174886],"iteration":278,"passed_time":1.401444532,"remaining_time":0.1054850723},
{"learn":[0.6647320211],"iteration":279,"passed_time":1.407002759,"remaining_time":0.1005001971},
{"learn":[0.6642225283],"iteration":280,"passed_time":1.411279027,"remaining_time":0.09542456055},
{"learn":[0.6632552361],"iteration":281,"passed_time":1.415641881,"remaining_time":0.09036012007},
{"learn":[0.6621089683],"iteration":282,"passed_time":1.420187533,"remaining_time":0.08531161858},
{"learn":[0.6614385451],"iteration":283,"passed_time":1.425229284,"remaining_time":0.08029460758},
{"learn":[0.6604925467],"iteration":284,"passed_time":1.4304415,"remaining_time":0.07528639474},
{"learn":[0.6597885558],"iteration":285,"passed_time":1.435743344,"remaining_time":0.0702811427},
{"learn":[0.6590192284],"iteration":286,"passed_time":1.441455284,"remaining_time":0.06529239964},
{"learn":[0.6583082785],"iteration":287,"passed_time":1.44702722,"remaining_time":0.06029280085},
{"learn":[0.656809992],"iteration":288,"passed_time":1.452637366,"remaining_time":0.05529069559},
{"learn":[0.6559640309],"iteration":289,"passed_time":1.45715085,"remaining_time":0.05024658104},
{"learn":[0.6550852052],"iteration":290,"passed_time":1.461969178,"remaining_time":0.04521554157},
{"learn":[0.6540782248],"iteration":291,"passed_time":1.466831465,"remaining_time":0.04018716342},
{"learn":[0.6533638853],"iteration":292,"passed_time":1.471513205,"remaining_time":0.03515560557},
{"learn":[0.6524262743],"iteration":293,"passed_time":1.476398201,"remaining_time":0.03013057553},
{"learn":[0.6518614217],"iteration":294,"passed_time":1.480763305,"remaining_time":0.02509768313},
{"learn":[0.6513769374],"iteration":295,"passed_time":1.485373084,"remaining_time":0.02007260924},
{"learn":[0.6502619211],"iteration":296,"passed_time":1.490152577,"remaining_time":0.01505204623},
{"learn":[0.6493898684],"iteration":297,"passed_time":1.494983321,"remaining_time":0.01003344511},
{"learn":[0.648882644],"iteration":298,"passed_time":1.499469138,"remaining_time":0.005014946949},
{"learn":[0.6483661394],"iteration":299,"passed_time":1.504098876,"remaining_time":0}
]}